MANIFEST.in
requirements-dev.txt
requirements-test.txt
requirements.txt
setup.py
pycame/__init__.py
pycame/came_manager.py
pycame/const.py
pycame/exceptions.py
pycame/models.py
pycame.egg-info/PKG-INFO
pycame.egg-info/SOURCES.txt
pycame.egg-info/dependency_links.txt
pycame.egg-info/requires.txt
pycame.egg-info/top_level.txt
pycame/devices/__init__.py
pycame/devices/base.py
pycame/devices/came_analog_sensor.py
pycame/devices/came_light.py
pycame/devices/came_opening.py
pycame/devices/came_thermo.py